alldebrid/__init__.py
alldebrid/client.py
alldebrid/response.py
alldebrid/models/__init__.py
alldebrid/models/error.py
alldebrid/models/link.py
alldebrid/models/magnet.py
alldebrid/models/pin.py
alldebrid-0.2.1.dist-info/METADATA
alldebrid-0.2.1.dist-info/WHEEL
alldebrid-0.2.1.dist-info/top_level.txt
alldebrid-0.2.1.dist-info/RECORD
