Metadata-Version: 2.4
Name: alldebrid
Version: 0.2.1
Summary: Lightweight async wrapper for AllDebrid API
Requires-Python: >=3.9
Requires-Dist: httpx>=0.28.1
Requires-Dist: pydantic>=2.11.7
